sPyBlocks/__init__.py
sPyBlocks/connection_functions.py
sPyBlocks/constant_spike_source.py
sPyBlocks/neural_and.py
sPyBlocks/neural_decoder.py
sPyBlocks/neural_encoder.py
sPyBlocks/neural_flank_detector.py
sPyBlocks/neural_latch_d.py
sPyBlocks/neural_latch_sr.py
sPyBlocks/neural_memory.py
sPyBlocks/neural_muxdemux.py
sPyBlocks/neural_not.py
sPyBlocks/neural_or.py
sPyBlocks/neural_oscillator.py
sPyBlocks/neural_xor.py
sPyBlocks/trace_functions.py
sPyBlocks-0.0.1.dist-info/LICENSE
sPyBlocks-0.0.1.dist-info/METADATA
sPyBlocks-0.0.1.dist-info/WHEEL
sPyBlocks-0.0.1.dist-info/top_level.txt
sPyBlocks-0.0.1.dist-info/RECORD
