Metadata-Version: 2.1
Name: sPyBlocks
Version: 0.0.1
Summary: A small example package
Home-page: https://github.com/alvayus/spyblocks
Author: Alvaro Ayuso-Martinez
Author-email: aayuso@us.es
License-File: LICENSE
